imagenation/__init__.py
imagenation/__main__.py
imagenation/cli.py
imagenation/generator.py
imagenation-1.0.1.dist-info/licenses/LICENSE
imagenation-1.0.1.dist-info/METADATA
imagenation-1.0.1.dist-info/WHEEL
imagenation-1.0.1.dist-info/entry_points.txt
imagenation-1.0.1.dist-info/top_level.txt
imagenation-1.0.1.dist-info/RECORD
