Metadata-Version: 2.4
Name: imagenation
Version: 1.0.1
Summary: Generate AI Images in Batches with Google's Imagen
Author-email: "Pedro M. Sosa" <konukoii@gmail.com>
Maintainer-email: "Pedro M. Sosa" <konukoii@gmail.com>
License: BSD-3-Clause
Project-URL: Homepage, https://github.com/pmsosa/imagenation
Project-URL: Repository, https://github.com/pmsosa/imagenation
Project-URL: Issues, https://github.com/pmsosa/imagenation/issues
Keywords: ai,image-generation,imagen,google-gemini,batch-processing,text-to-image,computer-vision
Classifier: Development Status :: 4 - Beta
Classifier: Intended Audience :: Developers
Classifier: License :: OSI Approved :: BSD License
Classifier: Programming Language :: Python :: 3
Classifier: Programming Language :: Python :: 3.7
Classifier: Programming Language :: Python :: 3.8
Classifier: Programming Language :: Python :: 3.9
Classifier: Programming Language :: Python :: 3.10
Classifier: Programming Language :: Python :: 3.11
Classifier: Programming Language :: Python :: 3.12
Classifier: Topic :: Software Development :: Libraries :: Python Modules
Classifier: Topic :: Multimedia :: Graphics
Classifier: Topic :: Scientific/Engineering :: Artificial Intelligence
Requires-Python: >=3.7
License-File: LICENSE
Requires-Dist: google-genai
Requires-Dist: pillow
Requires-Dist: python-dotenv
Dynamic: license-file
